iqcc_cloud_client/__init__.py
iqcc_cloud_client/accounting.py
iqcc_cloud_client/cli.py
iqcc_cloud_client/computers.py
iqcc_cloud_client/interfaces.py
iqcc_cloud_client/qmm_cloud.py
iqcc_cloud_client/runtime.py
iqcc_cloud_client/state.py
iqcc_cloud_client/tokens.py
iqcc_cloud_client/utilities.py
iqcc_cloud_client-0.15.4.dist-info/METADATA
iqcc_cloud_client-0.15.4.dist-info/WHEEL
iqcc_cloud_client-0.15.4.dist-info/entry_points.txt
iqcc_cloud_client-0.15.4.dist-info/licenses/LICENSE
iqcc_cloud_client-0.15.4.dist-info/RECORD
