Metadata-Version: 2.4
Name: iqcc-cloud-client
Version: 0.15.4
Summary: Access to IQCC quantum cloud
Author-email: Nikola Sibalic <nikola@quantum-machines.co>
License: BSD3
License-File: LICENSE
Classifier: Development Status :: 4 - Beta
Classifier: Intended Audience :: Education
Classifier: Intended Audience :: Science/Research
Classifier: License :: OSI Approved :: BSD License
Classifier: Programming Language :: Python
Classifier: Programming Language :: Python :: 3
Classifier: Topic :: Scientific/Engineering
Classifier: Topic :: Scientific/Engineering :: Physics
Requires-Python: >=3.10
Requires-Dist: arrow>=1.3.0
Requires-Dist: cryptography>=44.0.2
Requires-Dist: deepdiff>=8.6.1
Requires-Dist: h11>=0.16.0
Requires-Dist: h2>=4.3.0
Requires-Dist: httpx>=0.23.3
Requires-Dist: ipywidgets>=8.1.5
Requires-Dist: jsonschema>=4.24.0
Requires-Dist: plotext>=5.3.2
Requires-Dist: protobuf>=4.25.8
Requires-Dist: pydantic-extra-types[pendulum]>=2.10.3
Requires-Dist: pydantic>=2.9.1
Requires-Dist: pyjwt>=2.10.1
Requires-Dist: qiskit>=1.4.1
Requires-Dist: qm-qua>=1.2.4
Requires-Dist: rich[jupyter]>=13.8.0
Requires-Dist: toml>=0.10.2
Requires-Dist: typer>=0.15.1
Requires-Dist: urllib3>=2.6.3
